bioDAG/DAG.py
bioDAG/MeSH.py
bioDAG/__init__.py
bioDAG/Raw Data/MeSHTerm/meshTerm.2024_1_15.json
bioDAG/Raw Data/MeSHTerm/meshTerm.2024_1_16.json
biodag-0.0.4.dist-info/METADATA
biodag-0.0.4.dist-info/WHEEL
biodag-0.0.4.dist-info/licenses/LICENSE
biodag-0.0.4.dist-info/RECORD
